py_flow_mapper/__init__.py
py_flow_mapper/analyzer.py
py_flow_mapper/cli.py
py_flow_mapper/mermaid_generator.py
py_flow_mapper/utils.py
py_flow_mapper-0.1.0b8.dev0.dist-info/licenses/LICENSE
py_flow_mapper-0.1.0b8.dev0.dist-info/METADATA
py_flow_mapper-0.1.0b8.dev0.dist-info/WHEEL
py_flow_mapper-0.1.0b8.dev0.dist-info/entry_points.txt
py_flow_mapper-0.1.0b8.dev0.dist-info/top_level.txt
py_flow_mapper-0.1.0b8.dev0.dist-info/RECORD
