Metadata-Version: 2.4
Name: py-flow-mapper
Version: 0.1.0b8.dev0
Summary: Python project analyzer and visualization tool
Home-page: https://github.com/ArunKoundinya/py-flow-mapper
Author: Arun Koundinya Parasa
Author-email: parasa.arunkoundinya@gmail.com
License: MIT
Project-URL: Documentation, https://arunkoundinya.github.io/py-flow-mapper/
Project-URL: Source, https://github.com/ArunKoundinya/py-flow-mapper
Project-URL: Issues, https://github.com/ArunKoundinya/py-flow-mapper/issues
Project-URL: Changelog, https://github.com/ArunKoundinya/py-flow-mapper/releases
Keywords: static-analysis,call-graph,data-flow,mermaid,python-analysis
Classifier: Development Status :: 4 - Beta
Classifier: Intended Audience :: Developers
Classifier: Topic :: Software Development :: Documentation
Classifier: Topic :: Software Development :: Quality Assurance
Classifier: License :: OSI Approved :: MIT License
Classifier: Programming Language :: Python :: 3
Classifier: Programming Language :: Python :: 3.7
Classifier: Programming Language :: Python :: 3.8
Classifier: Programming Language :: Python :: 3.9
Classifier: Programming Language :: Python :: 3.10
Classifier: Programming Language :: Python :: 3.11
Classifier: Programming Language :: Python :: 3.12
Requires-Python: >=3.7
License-File: LICENSE
Requires-Dist: astunparse>=1.6.3; python_version < "3.9"
Dynamic: author
Dynamic: author-email
Dynamic: classifier
Dynamic: description
Dynamic: description-content-type
Dynamic: home-page
Dynamic: keywords
Dynamic: license
Dynamic: license-file
Dynamic: project-url
Dynamic: requires-dist
Dynamic: requires-python
Dynamic: summary
